{"id":"5fb0bc8e32cd6","brand":"dell","name":"New Inspiron 14 5000 2-in-1 Laptop (Titan Grey)","price":"$783.99","description":"Includes a 512GB solid state drive to handle all of your storage needs. Upgraded to an aluminum metal cover.","meta":{"address":"\/\/www.dell.com\/en-us\/member\/shop\/dell-laptops\/new-inspiron-14-5000-2-in-1-laptop-titan-grey\/spd\/inspiron-14-5406-2-in-1-laptop\/n25406ejuhh","image_address":"\/\/i.dell.com\/sites\/csimages\/App-Merchandizing_Images\/all\/Hellcat_N5_14_gray_thumbnail.png"}}